uiautomatoreventparser/LICENSE.txt
uiautomatoreventparser/README.MD
uiautomatoreventparser/__init__.py
uiautomatoreventparser/requirements.txt
uiautomatoreventparser/thirdparty.json
uiautomatoreventparser-0.11.dist-info/LICENSE.rst
uiautomatoreventparser-0.11.dist-info/METADATA
uiautomatoreventparser-0.11.dist-info/WHEEL
uiautomatoreventparser-0.11.dist-info/top_level.txt
uiautomatoreventparser-0.11.dist-info/RECORD
