Metadata-Version: 2.1
Name: uiautomatoreventparser
Version: 0.11
Summary: Interacting with uiautomator events
Home-page: https://github.com/hansalemaos/uiautomatoreventparser
Author: Johannes Fischer
Author-email: aulasparticularesdealemaosp@gmail.com
License: MIT
Keywords: uiautomator,events
Classifier: Development Status :: 4 - Beta
Classifier: Programming Language :: Python :: 3 :: Only
Classifier: Programming Language :: Python :: 3.10
Classifier: Topic :: Software Development :: Libraries :: Python Modules
Classifier: Topic :: Utilities
License-File: LICENSE.rst
Requires-Dist: adbshellexecuter
Requires-Dist: exceptdrucker
Requires-Dist: mymulti-key-dict
